qctrlreleasenoter/__init__.py
qctrlreleasenoter/cli.py
qctrlreleasenoter/generate_release_notes.py
qctrl_release_noter-0.14.1.dist-info/LICENSE
qctrl_release_noter-0.14.1.dist-info/METADATA
qctrl_release_noter-0.14.1.dist-info/WHEEL
qctrl_release_noter-0.14.1.dist-info/entry_points.txt
qctrl_release_noter-0.14.1.dist-info/RECORD
